mopidy_audioteka/__init__.py
mopidy_audioteka/audioteka.py
mopidy_audioteka/backend.py
mopidy_audioteka/exceptions.py
mopidy_audioteka/ext.conf
mopidy_audioteka/library.py
mopidy_audioteka/playback.py
mopidy_audioteka/translator.py
Mopidy_Audioteka-0.3.1.dist-info/LICENSE
Mopidy_Audioteka-0.3.1.dist-info/METADATA
Mopidy_Audioteka-0.3.1.dist-info/WHEEL
Mopidy_Audioteka-0.3.1.dist-info/entry_points.txt
Mopidy_Audioteka-0.3.1.dist-info/top_level.txt
Mopidy_Audioteka-0.3.1.dist-info/RECORD
