Metadata-Version: 2.1
Name: Mopidy-Audioteka
Version: 0.3.1
Summary: Mopidy backend extension for Audioteka
Home-page: https://github.com/jedrus2000/mopidy-audioteka
Author: Andrzej Bargański
Author-email: a.barganski@gmail.com
License: Apache License, Version 2.0
Platform: UNKNOWN
Classifier: Environment :: No Input/Output (Daemon)
Classifier: Intended Audience :: End Users/Desktop
Classifier: License :: OSI Approved :: Apache Software License
Classifier: Operating System :: OS Independent
Classifier: Programming Language :: Python :: 3
Classifier: Programming Language :: Python :: 3.7
Classifier: Programming Language :: Python :: 3.8
Classifier: Programming Language :: Python :: 3.9
Classifier: Topic :: Multimedia :: Sound/Audio :: Players
License-File: LICENSE
Requires-Dist: setuptools
Requires-Dist: Mopidy (>=3.0)
Requires-Dist: Pykka (>=2.0.1)
Requires-Dist: audtekapi (>=0.3.0)
